{"count":1,"self":12.3807552,"total":13.04628,"children":{"AgentResetIfDone":{"count":583,"self":0.006006,"total":0.006006,"children":null},"AgentSendState":{"count":583,"self":0.004495,"total":0.004961,"children":{"CollectObservations":{"count":59,"self":0.000466,"total":0.000466,"children":null}}},"DecideAction":{"count":583,"self":0.630844,"total":0.630844,"children":null},"AcademyStep":{"count":583,"self":0.001248,"total":0.001248,"children":null},"AgentAct":{"count":583,"self":0.021202,"total":0.021202,"children":null}}}